odoo8_addon_project_task_add_very_high-8.0.1.0.0.99.dev6-py3.8-nspkg.pth
odoo_addons/project_task_add_very_high/README.rst
odoo_addons/project_task_add_very_high/__init__.py
odoo_addons/project_task_add_very_high/__openerp__.py
odoo_addons/project_task_add_very_high/hooks.py
odoo_addons/project_task_add_very_high/i18n/ar.po
odoo_addons/project_task_add_very_high/i18n/ca.po
odoo_addons/project_task_add_very_high/i18n/de.po
odoo_addons/project_task_add_very_high/i18n/el.po
odoo_addons/project_task_add_very_high/i18n/es.po
odoo_addons/project_task_add_very_high/i18n/es_CR.po
odoo_addons/project_task_add_very_high/i18n/es_MX.po
odoo_addons/project_task_add_very_high/i18n/es_VE.po
odoo_addons/project_task_add_very_high/i18n/fi.po
odoo_addons/project_task_add_very_high/i18n/fr.po
odoo_addons/project_task_add_very_high/i18n/gl.po
odoo_addons/project_task_add_very_high/i18n/hr.po
odoo_addons/project_task_add_very_high/i18n/hr_HR.po
odoo_addons/project_task_add_very_high/i18n/hu.po
odoo_addons/project_task_add_very_high/i18n/it.po
odoo_addons/project_task_add_very_high/i18n/ja.po
odoo_addons/project_task_add_very_high/i18n/lt.po
odoo_addons/project_task_add_very_high/i18n/lv.po
odoo_addons/project_task_add_very_high/i18n/mk.po
odoo_addons/project_task_add_very_high/i18n/mn.po
odoo_addons/project_task_add_very_high/i18n/nl.po
odoo_addons/project_task_add_very_high/i18n/pl.po
odoo_addons/project_task_add_very_high/i18n/project_task_add_very_high.pot
odoo_addons/project_task_add_very_high/i18n/pt.po
odoo_addons/project_task_add_very_high/i18n/pt_BR.po
odoo_addons/project_task_add_very_high/i18n/pt_PT.po
odoo_addons/project_task_add_very_high/i18n/ro.po
odoo_addons/project_task_add_very_high/i18n/sl.po
odoo_addons/project_task_add_very_high/i18n/sv.po
odoo_addons/project_task_add_very_high/i18n/tr.po
odoo_addons/project_task_add_very_high/i18n/uk.po
odoo_addons/project_task_add_very_high/i18n/zh_CN.po
odoo_addons/project_task_add_very_high/models/__init__.py
odoo8_addon_project_task_add_very_high-8.0.1.0.0.99.dev6.dist-info/METADATA
odoo8_addon_project_task_add_very_high-8.0.1.0.0.99.dev6.dist-info/WHEEL
odoo8_addon_project_task_add_very_high-8.0.1.0.0.99.dev6.dist-info/namespace_packages.txt
odoo8_addon_project_task_add_very_high-8.0.1.0.0.99.dev6.dist-info/top_level.txt
odoo8_addon_project_task_add_very_high-8.0.1.0.0.99.dev6.dist-info/RECORD
