Metadata-Version: 2.1
Name: odoo8-addon-project-task-add-very-high
Version: 8.0.1.0.0.99.dev6
Summary: Adds an extra option 'Very High' on tasks
Home-page: http://www.onestein.eu
Author: Onestein, Odoo Community Association (OCA)
Author-email: support@odoo-community.org
License: AGPL-3
Platform: UNKNOWN
Classifier: Programming Language :: Python
Classifier: Framework :: Odoo
Classifier: Framework :: Odoo :: 8.0
Classifier: License :: OSI Approved :: GNU Affero General Public License v3
Requires-Python: ~=2.7
Requires-Dist: odoo (<9.0a,>=8.0a)
